datasifter/__init__.py
datasifter/bw_eng.txt
datasifter/bw_ru.txt
datasifter-0.0.5.1.dist-info/METADATA
datasifter-0.0.5.1.dist-info/WHEEL
datasifter-0.0.5.1.dist-info/RECORD
