Metadata-Version: 2.1
Name: datasifter
Version: 0.0.5.1
Summary: A module that simplifies working with conditions through filtering. For example: determining whether a text is a link
Home-page: https://github.com/RREKONI/DataSifter
License: GPL-3.0-only
Keywords: filters,filter,datasift
Author: Rekoni
Author-email: nilka.gacha@gmail.com
Requires-Python: >=3.10
Classifier: Development Status :: 5 - Production/Stable
Classifier: License :: OSI Approved :: GNU General Public License v3 (GPLv3)
Classifier: Operating System :: Microsoft :: Windows :: Windows 10
Classifier: Operating System :: Microsoft :: Windows :: Windows 11
Classifier: Operating System :: POSIX :: Linux
Classifier: Programming Language :: Python :: 3
Classifier: Programming Language :: Python :: 3.10
Classifier: Programming Language :: Python :: 3.11
Classifier: Programming Language :: Python :: 3.12
Classifier: Programming Language :: Python :: 3.13
Classifier: Programming Language :: Python :: 3.14
Classifier: Topic :: Software Development :: Libraries :: Python Modules
Classifier: Topic :: Text Processing :: Filters
Requires-Dist: requests (>=2.32.3)
Project-URL: Repository, https://github.com/RREKONI/DataSifter
